JavascriptWanquanShouce2018Ban/README.md
JavascriptWanquanShouce2018Ban/__init__.py
JavascriptWanquanShouce2018Ban/__main__.py
JavascriptWanquanShouce2018Ban/file.epub
JavascriptWanquanShouce2018Ban/index.html
JavascriptWanquanShouce2018Ban/css/__init__.py
JavascriptWanquanShouce2018Ban/css/annotations.css
JavascriptWanquanShouce2018Ban/css/main.css
JavascriptWanquanShouce2018Ban/css/normalize.css
JavascriptWanquanShouce2018Ban/css/popup.css
JavascriptWanquanShouce2018Ban/font/__init__.py
JavascriptWanquanShouce2018Ban/font/fontello.eot
JavascriptWanquanShouce2018Ban/font/fontello.svg
JavascriptWanquanShouce2018Ban/font/fontello.ttf
JavascriptWanquanShouce2018Ban/font/fontello.woff
JavascriptWanquanShouce2018Ban/img/__init__.py
JavascriptWanquanShouce2018Ban/img/annotator-glyph-sprite.png
JavascriptWanquanShouce2018Ban/img/annotator-icon-sprite.png
JavascriptWanquanShouce2018Ban/img/apple-touch-icon.png
JavascriptWanquanShouce2018Ban/img/cancelfullscreen.png
JavascriptWanquanShouce2018Ban/img/close.png
JavascriptWanquanShouce2018Ban/img/fullscreen.png
JavascriptWanquanShouce2018Ban/img/loader.gif
JavascriptWanquanShouce2018Ban/img/menu-icon.png
JavascriptWanquanShouce2018Ban/img/save.png
JavascriptWanquanShouce2018Ban/img/saved.png
JavascriptWanquanShouce2018Ban/img/settings-s.png
JavascriptWanquanShouce2018Ban/img/settings.png
JavascriptWanquanShouce2018Ban/img/star.png
JavascriptWanquanShouce2018Ban/js/__init__.py
JavascriptWanquanShouce2018Ban/js/epub.js
JavascriptWanquanShouce2018Ban/js/epub.min.js
JavascriptWanquanShouce2018Ban/js/epub.min.map
JavascriptWanquanShouce2018Ban/js/hooks.min.js
JavascriptWanquanShouce2018Ban/js/hooks.min.map
JavascriptWanquanShouce2018Ban/js/reader.js
JavascriptWanquanShouce2018Ban/js/reader.js.map
JavascriptWanquanShouce2018Ban/js/reader.min.js
JavascriptWanquanShouce2018Ban/js/reader.min.map
JavascriptWanquanShouce2018Ban/js/hooks/__init__.py
JavascriptWanquanShouce2018Ban/js/hooks/extensions/__init__.py
javascript_wanquan_shouce_2018_ban-2024.3.3.0.dist-info/METADATA
javascript_wanquan_shouce_2018_ban-2024.3.3.0.dist-info/WHEEL
javascript_wanquan_shouce_2018_ban-2024.3.3.0.dist-info/entry_points.txt
javascript_wanquan_shouce_2018_ban-2024.3.3.0.dist-info/top_level.txt
javascript_wanquan_shouce_2018_ban-2024.3.3.0.dist-info/RECORD
